{
  "cirq_type": "Circuit",
  "moments": [
    {
      "cirq_type": "Moment",
      "operations": [
        {
          "cirq_type": "GateOperation",
          "gate": {
            "cirq_type": "Ry",
            "rads": 0.10788967460393906
          },
          "qubits": [
            {
              "cirq_type": "NamedQubit",
              "name": "q_0"
            }
          ]
        }
      ]
    },
    {
      "cirq_type": "Moment",
      "operations": [
        {
          "cirq_type": "GateOperation",
          "gate": {
            "cirq_type": "Ry",
            "rads": 0.06844686716794968
          },
          "qubits": [
            {
              "cirq_type": "NamedQubit",
              "name": "q_0"
            }
          ]
        }
      ]
    },
    {
      "cirq_type": "Moment",
      "operations": [
        {
          "cirq_type": "GateOperation",
          "gate": {
            "cirq_type": "Ry",
            "rads": 0.047921884804964066
          },
          "qubits": [
            {
              "cirq_type": "NamedQubit",
              "name": "q_0"
            }
          ]
        }
      ]
    }
  ]
}