{
  "n_qubits": 3,
  "p_values": [
    0.001,
    0.005,
    0.01,
    0.02,
    0.05,
    0.08,
    0.1
  ],
  "n_shots": 1000,
  "n_repetitions": 5,
  "base_seed": 42,
  "baseline": {
    "true_p": [
      0.001,
      0.005,
      0.01,
      0.02,
      0.05,
      0.08,
      0.1
    ],
    "recovered_p_mean": [
      0.0009983444552852873,
      0.0049891486644513885,
      0.00999493991584368,
      0.020023699403013788,
      0.0499740777891219,
      0.07995496533035175,
      0.09997591975561418
    ],
    "recovered_p_std": [
      9.932081871613983e-06,
      9.073498184896791e-06,
      8.992329313605656e-06,
      1.451326591835622e-05,
      6.71085986673449e-05,
      0.0001002541210445556,
      0.0002364594440265927
    ],
    "observed_fidelity_mean": [
      0.9747454280539956,
      0.8808792982060536,
      0.777563550286051,
      0.6110649840910035,
      0.326452148916641,
      0.20828241934117261,
      0.17109546246827922
    ],
    "observed_fidelity_std": [
      0.00024697579357476485,
      0.0002029951765475857,
      0.0001718767837901544,
      0.00020738112608478985,
      0.00039857094133394455,
      0.0002455412914661745,
      0.0003236360698739007
    ],
    "recovery_error_mean": [
      -1.6555447147129782e-06,
      -1.0851335548611036e-05,
      -5.060084156320588e-06,
      2.3699403013786868e-05,
      -2.5922210878104313e-05,
      -4.503466964826397e-05,
      -2.4080244385835116e-05
    ],
    "recovery_error_std": [
      9.932081871613983e-06,
      9.073498184896791e-06,
      8.992329313605658e-06,
      1.4513265918356221e-05,
      6.71085986673449e-05,
      0.0001002541210445556,
      0.0002364594440265927
    ],
    "per_seed_data": [
      [
        {
          "seed": 0,
          "noise_seed": 42000000,
          "recovered_p": 0.0010135395563065472,
          "observed_fidelity": 0.9743674316286842,
          "recovery_error": 1.3539556306547181e-05
        },
        {
          "seed": 1,
          "noise_seed": 42000001,
          "recovered_p": 0.0010024168284649979,
          "observed_fidelity": 0.9746441681929192,
          "recovery_error": 2.4168284649978694e-06
        },
        {
          "seed": 2,
          "noise_seed": 42000002,
          "recovered_p": 0.000990533830135967,
          "observed_fidelity": 0.9749382438700824,
          "recovery_error": -9.46616986403307e-06
        },
        {
          "seed": 3,
          "noise_seed": 42000003,
          "recovered_p": 0.0009958155715497387,
          "observed_fidelity": 0.9748091143247418,
          "recovery_error": -4.184428450261339e-06
        },
        {
          "seed": 4,
          "noise_seed": 42000004,
          "recovered_p": 0.0009894164899691845,
          "observed_fidelity": 0.9749681822535505,
          "recovery_error": -1.0583510030815532e-05
        }
      ],
      [
        {
          "seed": 0,
          "noise_seed": 42001000,
          "recovered_p": 0.004985427908260311,
          "observed_fidelity": 0.8809626411521838,
          "recovery_error": -1.4572091739688785e-05
        },
        {
          "seed": 1,
          "noise_seed": 42001001,
          "recovered_p": 0.0049855925765478065,
          "observed_fidelity": 0.880959078265129,
          "recovery_error": -1.4407423452193584e-05
        },
        {
          "seed": 2,
          "noise_seed": 42001002,
          "recovered_p": 0.00500230685036058,
          "observed_fidelity": 0.8805849580454083,
          "recovery_error": 2.3068503605802246e-06
        },
        {
          "seed": 3,
          "noise_seed": 42001003,
          "recovered_p": 0.004993704350734231,
          "observed_fidelity": 0.8807771686527464,
          "recovery_error": -6.295649265769532e-06
        },
        {
          "seed": 4,
          "noise_seed": 42001004,
          "recovered_p": 0.004978711636354017,
          "observed_fidelity": 0.8811126449148008,
          "recovery_error": -2.12883636459835e-05
        }
      ],
      [
        {
          "seed": 0,
          "noise_seed": 42002000,
          "recovered_p": 0.00999826545224001,
          "observed_fidelity": 0.7775001342188066,
          "recovery_error": -1.7345477599899073e-06
        },
        {
          "seed": 1,
          "noise_seed": 42002001,
          "recovered_p": 0.009998845546305916,
          "observed_fidelity": 0.7774890622321068,
          "recovery_error": -1.1544536940837763e-06
        },
        {
          "seed": 2,
          "noise_seed": 42002002,
          "recovered_p": 0.009997574674231373,
          "observed_fidelity": 0.7775125187082168,
          "recovery_error": -2.4253257686276952e-06
        },
        {
          "seed": 3,
          "noise_seed": 42002003,
          "recovered_p": 0.010000996143638013,
          "observed_fidelity": 0.7774480849600756,
          "recovery_error": 9.961436380125782e-07
        },
        {
          "seed": 4,
          "noise_seed": 42002004,
          "recovered_p": 0.009979017762803086,
          "observed_fidelity": 0.7778679513110496,
          "recovery_error": -2.098223719691414e-05
        }
      ],
      [
        {
          "seed": 0,
          "noise_seed": 42003000,
          "recovered_p": 0.020027269816638774,
          "observed_fidelity": 0.6110144209483419,
          "recovery_error": 2.726981663877387e-05
        },
        {
          "seed": 1,
          "noise_seed": 42003001,
          "recovered_p": 0.02003898314156714,
          "observed_fidelity": 0.6108469660047574,
          "recovery_error": 3.8983141567139334e-05
        },
        {
          "seed": 2,
          "noise_seed": 42003002,
          "recovered_p": 0.020003110391665163,
          "observed_fidelity": 0.6113596089803788,
          "recovery_error": 3.1103916651627206e-06
        },
        {
          "seed": 3,
          "noise_seed": 42003003,
          "recovered_p": 0.0200153259782996,
          "observed_fidelity": 0.6111838642071807,
          "recovery_error": 1.5325978299601112e-05
        },
        {
          "seed": 4,
          "noise_seed": 42003004,
          "recovered_p": 0.020033807686898258,
          "observed_fidelity": 0.6109200603143592,
          "recovery_error": 3.3807686898257305e-05
        }
      ],
      [
        {
          "seed": 0,
          "noise_seed": 42004000,
          "recovered_p": 0.04998973919767629,
          "observed_fidelity": 0.3263584068259277,
          "recovery_error": -1.0260802323712459e-05
        },
        {
          "seed": 1,
          "noise_seed": 42004001,
          "recovered_p": 0.050017088938568065,
          "observed_fidelity": 0.3261959955199588,
          "recovery_error": 1.7088938568061984e-05
        },
        {
          "seed": 2,
          "noise_seed": 42004002,
          "recovered_p": 0.04986427027944239,
          "observed_fidelity": 0.3271048024632983,
          "recovery_error": -0.00013572972055761467
        },
        {
          "seed": 3,
          "noise_seed": 42004003,
          "recovered_p": 0.049963910572139336,
          "observed_fidelity": 0.3265120104675241,
          "recovery_error": -3.60894278606666e-05
        },
        {
          "seed": 4,
          "noise_seed": 42004004,
          "recovered_p": 0.05003537995778341,
          "observed_fidelity": 0.32608952930649604,
          "recovery_error": 3.537995778341019e-05
        }
      ],
      [
        {
          "seed": 0,
          "noise_seed": 42005000,
          "recovered_p": 0.07988230662381061,
          "observed_fidelity": 0.20845996592744398,
          "recovery_error": -0.00011769337618938724
        },
        {
          "seed": 1,
          "noise_seed": 42005001,
          "recovered_p": 0.08002207989685044,
          "observed_fidelity": 0.20812083417990646,
          "recovery_error": 2.2079896850435432e-05
        },
        {
          "seed": 2,
          "noise_seed": 42005002,
          "recovered_p": 0.08007378515254829,
          "observed_fidelity": 0.20799099245710648,
          "recovery_error": 7.378515254828633e-05
        },
        {
          "seed": 3,
          "noise_seed": 42005003,
          "recovered_p": 0.07996863418256403,
          "observed_fidelity": 0.20824599795749138,
          "recovery_error": -3.1365817435971555e-05
        },
        {
          "seed": 4,
          "noise_seed": 42005004,
          "recovered_p": 0.07982802079598532,
          "observed_fidelity": 0.20859430618391486,
          "recovery_error": -0.0001719792040146828
        }
      ],
      [
        {
          "seed": 0,
          "noise_seed": 42006000,
          "recovered_p": 0.09958467815609216,
          "observed_fidelity": 0.17163158076916066,
          "recovery_error": -0.00041532184390784266
        },
        {
          "seed": 1,
          "noise_seed": 42006001,
          "recovered_p": 0.09996462051640043,
          "observed_fidelity": 0.1711097483004455,
          "recovery_error": -3.53794835995791e-05
        },
        {
          "seed": 2,
          "noise_seed": 42006002,
          "recovered_p": 0.10013519178117827,
          "observed_fidelity": 0.17087769139163156,
          "recovery_error": 0.0001351917811782677
        },
        {
          "seed": 3,
          "noise_seed": 42006003,
          "recovered_p": 0.10018558022883894,
          "observed_fidelity": 0.170809589074062,
          "recovery_error": 0.00018558022883893854
        },
        {
          "seed": 4,
          "noise_seed": 42006004,
          "recovered_p": 0.10000952809556105,
          "observed_fidelity": 0.17104870280609638,
          "recovery_error": 9.528095561039951e-06
        }
      ]
    ],
    "noise_seeds": [
      [
        42000000,
        42000001,
        42000002,
        42000003,
        42000004
      ],
      [
        42001000,
        42001001,
        42001002,
        42001003,
        42001004
      ],
      [
        42002000,
        42002001,
        42002002,
        42002003,
        42002004
      ],
      [
        42003000,
        42003001,
        42003002,
        42003003,
        42003004
      ],
      [
        42004000,
        42004001,
        42004002,
        42004003,
        42004004
      ],
      [
        42005000,
        42005001,
        42005002,
        42005003,
        42005004
      ],
      [
        42006000,
        42006001,
        42006002,
        42006003,
        42006004
      ]
    ]
  },
  "robust": {
    "true_p": [
      0.001,
      0.005,
      0.01,
      0.02,
      0.05,
      0.08,
      0.1
    ],
    "recovered_p_mean": [
      0.001001205581112149,
      0.005006631191880514,
      0.010010088688034071,
      0.019968709177016857,
      0.04995843579313227,
      0.08008028837724333,
      0.09994514021020295
    ],
    "recovered_p_std": [
      1.1813692448583653e-05,
      2.9437349787240737e-05,
      2.5469805360755823e-05,
      5.867641772909784e-05,
      0.00011809072522604327,
      0.00015919604943828155,
      0.00015636510088517952
    ],
    "observed_fidelity_mean": [
      0.995341504844194,
      0.9768925397433449,
      0.9543191022257715,
      0.9108782464908286,
      0.7914229061866822,
      0.6872007422984453,
      0.6262608621954057
    ],
    "observed_fidelity_std": [
      5.4851553140966564e-05,
      0.0001342127600131021,
      0.0001141098251039905,
      0.00024997608210022165,
      0.00043846041333214515,
      0.0005120311435655189,
      0.0004567740400428579
    ],
    "recovery_error_mean": [
      1.2055811121490685e-06,
      6.631191880514774e-06,
      1.0088688034069413e-05,
      -3.129082298314254e-05,
      -4.1564206867727996e-05,
      8.028837724333992e-05,
      -5.4859789797059856e-05
    ],
    "recovery_error_std": [
      1.1813692448583653e-05,
      2.9437349787240737e-05,
      2.5469805360755823e-05,
      5.867641772909784e-05,
      0.00011809072522604327,
      0.00015919604943828152,
      0.00015636510088517955
    ],
    "per_seed_data": [
      [
        {
          "seed": 0,
          "noise_seed": 1452065410,
          "recovered_p": 0.0010017354536329566,
          "observed_fidelity": 0.9953389047104142,
          "recovery_error": 1.735453632956607e-06
        },
        {
          "seed": 1,
          "noise_seed": 1452065411,
          "recovered_p": 0.0010146870265438988,
          "observed_fidelity": 0.9952788885136745,
          "recovery_error": 1.4687026543898796e-05
        },
        {
          "seed": 2,
          "noise_seed": 1452065412,
          "recovered_p": 0.0010096607970430857,
          "observed_fidelity": 0.9953023396962094,
          "recovery_error": 9.660797043085706e-06
        },
        {
          "seed": 3,
          "noise_seed": 1452065413,
          "recovered_p": 0.0009848556779485527,
          "observed_fidelity": 0.9954174183891781,
          "recovery_error": -1.514432205144728e-05
        },
        {
          "seed": 4,
          "noise_seed": 1452065414,
          "recovered_p": 0.0009950889503922515,
          "observed_fidelity": 0.9953699729114941,
          "recovery_error": -4.911049607748486e-06
        }
      ],
      [
        {
          "seed": 0,
          "noise_seed": 1452066410,
          "recovered_p": 0.004985729453245214,
          "observed_fidelity": 0.9769877934417887,
          "recovery_error": -1.4270546754785798e-05
        },
        {
          "seed": 1,
          "noise_seed": 1452066411,
          "recovered_p": 0.005031414479846707,
          "observed_fidelity": 0.9767796294487227,
          "recovery_error": 3.141447984670708e-05
        },
        {
          "seed": 2,
          "noise_seed": 1452066412,
          "recovered_p": 0.0050024021055815925,
          "observed_fidelity": 0.9769118960349578,
          "recovery_error": 2.402105581592387e-06
        },
        {
          "seed": 3,
          "noise_seed": 1452066413,
          "recovered_p": 0.004972184224903711,
          "observed_fidelity": 0.9770495729973121,
          "recovery_error": -2.7815775096288846e-05
        },
        {
          "seed": 4,
          "noise_seed": 1452066414,
          "recovered_p": 0.005041425695825349,
          "observed_fidelity": 0.9767338067939427,
          "recovery_error": 4.1425695825349045e-05
        }
      ],
      [
        {
          "seed": 0,
          "noise_seed": 1452067410,
          "recovered_p": 0.010012412475858651,
          "observed_fidelity": 0.9543082949443641,
          "recovery_error": 1.2412475858650934e-05
        },
        {
          "seed": 1,
          "noise_seed": 1452067411,
          "recovered_p": 0.009997606198037341,
          "observed_fidelity": 0.9543754780138592,
          "recovery_error": -2.3938019626593143e-06
        },
        {
          "seed": 2,
          "noise_seed": 1452067412,
          "recovered_p": 0.010036817397589708,
          "observed_fidelity": 0.9541993679371704,
          "recovery_error": 3.681739758970744e-05
        },
        {
          "seed": 3,
          "noise_seed": 1452067413,
          "recovered_p": 0.00997367962962725,
          "observed_fidelity": 0.954482087063612,
          "recovery_error": -2.6320370372749646e-05
        },
        {
          "seed": 4,
          "noise_seed": 1452067414,
          "recovered_p": 0.010029927739057398,
          "observed_fidelity": 0.9542302831698521,
          "recovery_error": 2.992773905739765e-05
        }
      ],
      [
        {
          "seed": 0,
          "noise_seed": 1452068410,
          "recovered_p": 0.02001945900055098,
          "observed_fidelity": 0.9106636185187339,
          "recovery_error": 1.945900055097885e-05
        },
        {
          "seed": 1,
          "noise_seed": 1452068411,
          "recovered_p": 0.019912027393919472,
          "observed_fidelity": 0.9111271658842083,
          "recovery_error": -8.797260608052818e-05
        },
        {
          "seed": 2,
          "noise_seed": 1452068412,
          "recovered_p": 0.019941855325246078,
          "observed_fidelity": 0.9109886583947199,
          "recovery_error": -5.814467475392243e-05
        },
        {
          "seed": 3,
          "noise_seed": 1452068413,
          "recovered_p": 0.0199271161585346,
          "observed_fidelity": 0.9110500933345868,
          "recovery_error": -7.288384146540011e-05
        },
        {
          "seed": 4,
          "noise_seed": 1452068414,
          "recovered_p": 0.02004308800683316,
          "observed_fidelity": 0.9105616963218945,
          "recovery_error": 4.308800683315919e-05
        }
      ],
      [
        {
          "seed": 0,
          "noise_seed": 1452069410,
          "recovered_p": 0.04980960777625362,
          "observed_fidelity": 0.7919756226678404,
          "recovery_error": -0.0001903922237463801
        },
        {
          "seed": 1,
          "noise_seed": 1452069411,
          "recovered_p": 0.04996912569793772,
          "observed_fidelity": 0.7913832007955078,
          "recovery_error": -3.0874302062285086e-05
        },
        {
          "seed": 2,
          "noise_seed": 1452069412,
          "recovered_p": 0.050123680347601375,
          "observed_fidelity": 0.7908094952446336,
          "recovery_error": 0.0001236803476013723
        },
        {
          "seed": 3,
          "noise_seed": 1452069413,
          "recovered_p": 0.0498908248135943,
          "observed_fidelity": 0.7916738610138168,
          "recovery_error": -0.00010917518640569945
        },
        {
          "seed": 4,
          "noise_seed": 1452069414,
          "recovered_p": 0.049998940330274355,
          "observed_fidelity": 0.7912723512116122,
          "recovery_error": -1.0596697256476384e-06
        }
      ],
      [
        {
          "seed": 0,
          "noise_seed": 1452070410,
          "recovered_p": 0.07999095030723,
          "observed_fidelity": 0.687487889368107,
          "recovery_error": -9.049692770005113e-06
        },
        {
          "seed": 1,
          "noise_seed": 1452070411,
          "recovered_p": 0.08027323222017402,
          "observed_fidelity": 0.6865801646260392,
          "recovery_error": 0.00027323222017401616
        },
        {
          "seed": 2,
          "noise_seed": 1452070412,
          "recovered_p": 0.07995919215987445,
          "observed_fidelity": 0.6875900110408779,
          "recovery_error": -4.080784012555627e-05
        },
        {
          "seed": 3,
          "noise_seed": 1452070413,
          "recovered_p": 0.08023281756878393,
          "observed_fidelity": 0.6867101979060869,
          "recovery_error": 0.0002328175687839329
        },
        {
          "seed": 4,
          "noise_seed": 1452070414,
          "recovered_p": 0.07994524963015431,
          "observed_fidelity": 0.6876354485511154,
          "recovery_error": -5.475036984568804e-05
        }
      ],
      [
        {
          "seed": 0,
          "noise_seed": 1452071410,
          "recovered_p": 0.09998222505721037,
          "observed_fidelity": 0.6261524168419779,
          "recovery_error": -1.7774942789636206e-05
        },
        {
          "seed": 1,
          "noise_seed": 1452071411,
          "recovered_p": 0.09988941536250422,
          "observed_fidelity": 0.6264236858341399,
          "recovery_error": -0.00011058463749578917
        },
        {
          "seed": 2,
          "noise_seed": 1452071412,
          "recovered_p": 0.09988654993450503,
          "observed_fidelity": 0.6264320628979184,
          "recovery_error": -0.00011345006549497161
        },
        {
          "seed": 3,
          "noise_seed": 1452071413,
          "recovered_p": 0.09977530324794186,
          "observed_fidelity": 0.6267569838371325,
          "recovery_error": -0.00022469675205814832
        },
        {
          "seed": 4,
          "noise_seed": 1452071414,
          "recovered_p": 0.10019220744885325,
          "observed_fidelity": 0.6255391615658598,
          "recovery_error": 0.00019220744885324603
        }
      ]
    ],
    "noise_seeds": [
      [
        1452065410,
        1452065411,
        1452065412,
        1452065413,
        1452065414
      ],
      [
        1452066410,
        1452066411,
        1452066412,
        1452066413,
        1452066414
      ],
      [
        1452067410,
        1452067411,
        1452067412,
        1452067413,
        1452067414
      ],
      [
        1452068410,
        1452068411,
        1452068412,
        1452068413,
        1452068414
      ],
      [
        1452069410,
        1452069411,
        1452069412,
        1452069413,
        1452069414
      ],
      [
        1452070410,
        1452070411,
        1452070412,
        1452070413,
        1452070414
      ],
      [
        1452071410,
        1452071411,
        1452071412,
        1452071413,
        1452071414
      ]
    ]
  }
}